know/__init__.py
know/ai.py
know/cli.py
know/config.py
know/context_engine.py
know/diff.py
know/exceptions.py
know/generator.py
know/git_hooks.py
know/import_graph.py
know/index.py
know/knowledge_base.py
know/logger.py
know/mcp_server.py
know/models.py
know/parsers.py
know/quality.py
know/scanner.py
know/semantic_search.py
know/stats.py
know/token_counter.py
know/watcher.py
know_cli-0.3.0.dist-info/METADATA
know_cli-0.3.0.dist-info/WHEEL
know_cli-0.3.0.dist-info/entry_points.txt
know_cli-0.3.0.dist-info/RECORD
