Metadata-Version: 2.4
Name: know-cli
Version: 0.3.0
Summary: Context Intelligence for AI Coding Agents — smart, token-budgeted code context
Project-URL: Homepage, https://github.com/vic/know-cli
Project-URL: Repository, https://github.com/vic/know-cli
Author-email: Sushil Kumar <sushilk.1991@gmail.com>
License-Expression: MIT
Keywords: ai,cli,codebase,coding-agent,context,embeddings,llm,mcp,tokens
Classifier: Development Status :: 3 - Alpha
Classifier: Intended Audience :: Developers
Classifier: License :: OSI Approved :: MIT License
Classifier: Programming Language :: Python :: 3
Classifier: Programming Language :: Python :: 3.10
Classifier: Programming Language :: Python :: 3.11
Classifier: Programming Language :: Python :: 3.12
Classifier: Topic :: Software Development :: Documentation
Classifier: Topic :: Utilities
Requires-Python: >=3.10
Requires-Dist: anthropic>=0.8.0
Requires-Dist: click>=8.1.0
Requires-Dist: httpx>=0.24.0
Requires-Dist: pathspec>=0.11.0
Requires-Dist: pyyaml>=6.0
Requires-Dist: rich>=13.0.0
Requires-Dist: watchdog>=3.0.0
Requires-Dist: xxhash>=3.0.0
Provides-Extra: dev
Requires-Dist: black>=23.0.0; extra == 'dev'
Requires-Dist: mypy>=1.0.0; extra == 'dev'
Requires-Dist: pytest-asyncio>=0.21.0; extra == 'dev'
Requires-Dist: pytest-cov>=4.0.0; extra == 'dev'
Requires-Dist: pytest>=7.0.0; extra == 'dev'
Requires-Dist: ruff>=0.1.0; extra == 'dev'
Provides-Extra: mcp
Requires-Dist: mcp>=1.0.0; extra == 'mcp'
Provides-Extra: parser
Requires-Dist: tree-sitter-languages>=1.10.0; extra == 'parser'
Requires-Dist: tree-sitter>=0.20.0; extra == 'parser'
Provides-Extra: search
Requires-Dist: fastembed>=0.3.0; extra == 'search'
Requires-Dist: numpy>=1.24.0; extra == 'search'
